tests/test_stdlib/__init__.py
tests/test_stdlib/test_escrow.py
sapio_stdlib-0.1.0.dist-info/LICENSE
sapio_stdlib-0.1.0.dist-info/METADATA
sapio_stdlib-0.1.0.dist-info/WHEEL
sapio_stdlib-0.1.0.dist-info/top_level.txt
sapio_stdlib-0.1.0.dist-info/RECORD
